setup.py
chrisecho/__init__.py
chrisecho/test.py
chrisecho.egg-info/PKG-INFO
chrisecho.egg-info/SOURCES.txt
chrisecho.egg-info/dependency_links.txt
chrisecho.egg-info/not-zip-safe
chrisecho.egg-info/requires.txt
chrisecho.egg-info/top_level.txt