Metadata-Version: 1.1
Name: chrisecho
Version: 1.0.1
Summary: Echos something to the console.
Home-page: UNKNOWN
Author: Chris Lombaard
Author-email: chrislombaard@gmail.com
License: UNKNOWN
Platform: UNKNOWN
Classifier: Programming Language :: Python
Classifier: License :: OSI Approved :: BSD License
Classifier: Development Status :: 4 - Beta
Classifier: Operating System :: OS Independent
Classifier: Framework :: Django
Classifier: Intended Audience :: Developers
Classifier: Topic :: Internet :: WWW/HTTP :: Dynamic Content
